manila/__init__.py
manila/context.py
manila/coordination.py
manila/exception.py
manila/i18n.py
manila/manager.py
manila/opts.py
manila/policy.py
manila/quota.py
manila/rpc.py
manila/service.py
manila/ssh_utils.py
manila/test.py
manila/utils.py
manila/version.py
manila/api/__init__.py
manila/api/common.py
manila/api/extensions.py
manila/api/urlmap.py
manila/api/versions.py
manila/api/contrib/__init__.py
manila/api/middleware/__init__.py
manila/api/middleware/auth.py
manila/api/middleware/fault.py
manila/api/openstack/__init__.py
manila/api/openstack/api_version_request.py
manila/api/openstack/rest_api_version_history.rst
manila/api/openstack/urlmap.py
manila/api/openstack/versioned_method.py
manila/api/openstack/wsgi.py
manila/api/schemas/__init__.py
manila/api/schemas/availability_zones.py
manila/api/schemas/messages.py
manila/api/schemas/resource_locks.py
manila/api/v1/__init__.py
manila/api/v1/limits.py
manila/api/v1/router.py
manila/api/v1/scheduler_stats.py
manila/api/v1/security_service.py
manila/api/v1/share_manage.py
manila/api/v1/share_metadata.py
manila/api/v1/share_servers.py
manila/api/v1/share_snapshots.py
manila/api/v1/share_types_extra_specs.py
manila/api/v1/share_unmanage.py
manila/api/v1/shares.py
manila/api/v2/__init__.py
manila/api/v2/availability_zones.py
manila/api/v2/messages.py
manila/api/v2/metadata.py
manila/api/v2/quota_class_sets.py
manila/api/v2/quota_sets.py
manila/api/v2/resource_locks.py
manila/api/v2/router.py
manila/api/v2/services.py
manila/api/v2/share_access_metadata.py
manila/api/v2/share_accesses.py
manila/api/v2/share_backups.py
manila/api/v2/share_export_locations.py
manila/api/v2/share_group_snapshots.py
manila/api/v2/share_group_type_specs.py
manila/api/v2/share_group_types.py
manila/api/v2/share_groups.py
manila/api/v2/share_instance_export_locations.py
manila/api/v2/share_instances.py
manila/api/v2/share_network_subnets.py
manila/api/v2/share_networks.py
manila/api/v2/share_replica_export_locations.py
manila-21.0.0.dist-info/AUTHORS
manila-21.0.0.dist-info/LICENSE
manila-21.0.0.dist-info/METADATA
manila-21.0.0.dist-info/WHEEL
manila-21.0.0.dist-info/entry_points.txt
manila-21.0.0.dist-info/pbr.json
manila-21.0.0.dist-info/top_level.txt
manila-21.0.0.dist-info/RECORD
