Metadata-Version: 2.1
Name: manila
Version: 21.0.0
Summary: Shared Storage for OpenStack
Home-page: https://docs.openstack.org/manila/latest/
Author: OpenStack
Author-email: openstack-discuss@lists.openstack.org
Classifier: Environment :: OpenStack
Classifier: Intended Audience :: Information Technology
Classifier: Intended Audience :: System Administrators
Classifier: License :: OSI Approved :: Apache Software License
Classifier: Operating System :: POSIX :: Linux
Classifier: Programming Language :: Python
Classifier: Programming Language :: Python :: 3 :: Only
Classifier: Programming Language :: Python :: 3
Classifier: Programming Language :: Python :: 3.10
Classifier: Programming Language :: Python :: 3.11
Classifier: Programming Language :: Python :: 3.12
Requires-Python: >=3.10
License-File: LICENSE
License-File: AUTHORS
Requires-Dist: pbr >=5.5.0
Requires-Dist: alembic >=1.4.2
Requires-Dist: castellan >=3.7.0
Requires-Dist: defusedxml >=0.7.1
Requires-Dist: eventlet >=0.27.0
Requires-Dist: greenlet >=0.4.16
Requires-Dist: lxml >=4.5.2
Requires-Dist: netaddr >=0.8.0
Requires-Dist: oslo.config >=8.3.2
Requires-Dist: oslo.context >=3.1.1
Requires-Dist: oslo.db >=8.4.0
Requires-Dist: oslo.i18n >=5.0.1
Requires-Dist: oslo.log >=4.4.0
Requires-Dist: oslo.messaging >=14.1.0
Requires-Dist: oslo.middleware >=4.1.1
Requires-Dist: oslo.policy >=4.5.0
Requires-Dist: oslo.privsep >=2.4.0
Requires-Dist: oslo.reports >=2.2.0
Requires-Dist: oslo.rootwrap >=6.2.0
Requires-Dist: oslo.serialization >=4.0.1
Requires-Dist: oslo.service >=2.4.0
Requires-Dist: oslo.upgradecheck >=1.3.0
Requires-Dist: oslo.utils >=7.0.0
Requires-Dist: oslo.concurrency >=4.3.0
Requires-Dist: osprofiler >=3.4.0
Requires-Dist: paramiko >=2.7.2
Requires-Dist: Paste >=3.4.3
Requires-Dist: PasteDeploy >=2.1.0
Requires-Dist: pyparsing >=2.4.7
Requires-Dist: python-neutronclient >=6.7.0
Requires-Dist: keystoneauth1 >=4.2.1
Requires-Dist: keystonemiddleware >=9.1.0
Requires-Dist: requests >=2.23.0
Requires-Dist: tenacity >=6.3.1
Requires-Dist: Routes >=2.4.1
Requires-Dist: SQLAlchemy >=1.4.0
Requires-Dist: SQLAlchemy-Utils >=0.38.3
Requires-Dist: stevedore >=3.2.2
Requires-Dist: tooz >=2.7.1
Requires-Dist: python-cinderclient >=4.0.1
Requires-Dist: python-novaclient >=17.2.1
Requires-Dist: python-glanceclient >=3.2.2
Requires-Dist: WebOb >=1.8.6
Requires-Dist: cachetools >=4.2.1
Requires-Dist: packaging >=20.9
